README.rst
setup.py
mrfh/__init__.py
mrfh.egg-info/PKG-INFO
mrfh.egg-info/SOURCES.txt
mrfh.egg-info/dependency_links.txt
mrfh.egg-info/not-zip-safe
mrfh.egg-info/top_level.txt