Metadata-Version: 1.1
Name: mrfh
Version: 0.0.1
Summary: Multiprocess Rotating File Handler
Home-page: http://github.com/di/mrfh
Author: Dustin Ingram
Author-email: github@dustingram.com
License: MIT
Keywords: multi process rotating file handler concurrent multiprocess
Platform: UNKNOWN
Classifier: Development Status :: 4 - Beta
Classifier: Environment :: Console
Classifier: Natural Language :: English
Classifier: License :: OSI Approved :: MIT License
Classifier: Operating System :: OS Independent
Classifier: Programming Language :: Python
Classifier: Programming Language :: Python :: 2
Classifier: Programming Language :: Python :: 2.6
Classifier: Programming Language :: Python :: 2.7
Classifier: Programming Language :: Python :: 3
Classifier: Programming Language :: Python :: 3.0
Classifier: Programming Language :: Python :: 3.1
Classifier: Programming Language :: Python :: 3.2
Classifier: Programming Language :: Python :: 3.3
Classifier: Programming Language :: Python :: 3.4
Classifier: Intended Audience :: Developers
